{
  "version": "2.2.0",
  "summary": {
    "title": "SENG406 Threat Modelling",
    "owner": "Tara Lipscombe",
    "description": "Renew and Terminate a Registration",
    "id": 0
  },
  "detail": {
    "contributors": [],
    "diagrams": [
      {
        "id": 0,
        "title": "Renew and Terminate a Registration",
        "diagramType": "STRIDE",
        "placeholder": "New STRIDE diagram description",
        "thumbnail": "./public/content/images/thumbnail.stride.jpg",
        "version": "2.2.0",
        "cells": [
          {
            "position": {
              "x": 170,
              "y": 110
            },
            "size": {
              "width": 112.5,
              "height": 60
            },
            "attrs": {
              "body": {
                "stroke": "#333333",
                "strokeWidth": 1.5,
                "strokeDasharray": null
              }
            },
            "visible": true,
            "shape": "actor",
            "id": "f145ce34-8d29-4e6c-8c3f-c5bcdb86e15d",
            "zIndex": 1,
            "data": {
              "type": "tm.Actor",
              "name": "Actor",
              "description": "",
              "outOfScope": false,
              "reasonOutOfScope": "",
              "hasOpenThreats": false,
              "providesAuthentication": false,
              "threats": []
            }
          },
          {
            "shape": "trust-boundary-curve",
            "width": 200,
            "height": 100,
            "zIndex": 10,
            "connector": "smooth",
            "data": {
              "type": "tm.Boundary",
              "name": "",
              "description": "",
              "isTrustBoundary": true,
              "hasOpenThreats": false
            },
            "id": "b7ae4064-4342-4a61-a006-0708bc4f6c0c",
            "source": {
              "x": 399,
              "y": 50
            },
            "target": {
              "x": 400,
              "y": 410
            }
          },
          {
            "shape": "flow",
            "attrs": {
              "line": {
                "stroke": "red",
                "strokeWidth": 2.5,
                "targetMarker": {
                  "name": "block"
                },
                "sourceMarker": {
                  "name": ""
                },
                "strokeDasharray": null
              }
            },
            "width": 200,
            "height": 100,
            "zIndex": 10,
            "connector": "smooth",
            "data": {
              "type": "tm.Flow",
              "name": "USer Data",
              "description": "Data",
              "outOfScope": false,
              "reasonOutOfScope": "",
              "hasOpenThreats": true,
              "isBidirectional": false,
              "isEncrypted": false,
              "isPublicNetwork": false,
              "protocol": "",
              "threats": [
                {
                  "id": "f6a5132f-f161-43a1-9782-767eefbb5cce",
                  "title": "Threat",
                  "status": "Open",
                  "severity": "Medium",
                  "type": "Tampering",
                  "description": "YUP",
                  "mitigation": "NONDE",
                  "modelType": "STRIDE",
                  "new": false,
                  "number": 1,
                  "score": ""
                }
              ],
              "threatFrequency": {
                "tampering": 1,
                "informationDisclosure": 0,
                "denialOfService": 0
              }
            },
            "id": "b3e03090-937a-4850-92aa-4bb57ddae3a2",
            "source": {
              "x": 283,
              "y": 138
            },
            "target": {
              "cell": "5cde68d5-be21-43d5-a4e8-c8536d9cd7f3"
            },
            "vertices": [],
            "labels": [
              "USer Data"
            ]
          },
          {
            "position": {
              "x": 600,
              "y": 160
            },
            "size": {
              "width": 120,
              "height": 60
            },
            "attrs": {
              "topLine": {
                "strokeWidth": 1.5,
                "strokeDasharray": null
              },
              "bottomLine": {
                "strokeWidth": 1.5,
                "strokeDasharray": null
              }
            },
            "visible": true,
            "shape": "store",
            "id": "5cde68d5-be21-43d5-a4e8-c8536d9cd7f3",
            "zIndex": 11,
            "data": {
              "type": "tm.Store",
              "name": "Store",
              "description": "",
              "outOfScope": false,
              "reasonOutOfScope": "",
              "hasOpenThreats": false,
              "isALog": false,
              "isEncrypted": false,
              "isSigned": false,
              "storesCredentials": false,
              "storesInventory": false,
              "threats": []
            }
          }
        ]
      },
      {
        "id": 3,
        "title": "Declare a lost dog",
        "diagramType": "STRIDE",
        "placeholder": "New STRIDE diagram description",
        "thumbnail": "./public/content/images/thumbnail.stride.jpg",
        "version": "2.2.0",
        "cells": []
      },
      {
        "id": 4,
        "title": "Register a dog",
        "diagramType": "STRIDE",
        "placeholder": "New STRIDE diagram description",
        "thumbnail": "./public/content/images/thumbnail.stride.jpg",
        "version": "2.2.0",
        "cells": []
      },
      {
        "id": 5,
        "title": "Report of found dog",
        "diagramType": "STRIDE",
        "placeholder": "New STRIDE diagram description",
        "thumbnail": "./public/content/images/thumbnail.stride.jpg",
        "version": "2.2.0",
        "cells": []
      }
    ],
    "diagramTop": 6,
    "reviewer": "",
    "threatTop": 1
  }
}